Metadata-Version: 1.1
Name: perfecto-py37
Version: 0.1.0
Summary: Perfecto smart reporting lib
Home-page: https://gitlab.com/perfectops/perfecto-python37
Author: Perfecto PS
Author-email: Professional Services <professionalservices@perfectomobile.com>
License: http://www.apache.org/licenses/LICENSE-2.0
Keywords: Perfecto smart reporting python
Platform: any
Classifier: Development Status :: 3 - Alpha
Classifier: License :: OSI Approved :: MIT License
Classifier: Operating System :: OS Independent
Classifier: Programming Language :: Python
Classifier: Topic :: Software Development :: Testing
Classifier: Programming Language :: Python
Classifier: Programming Language :: Python :: 3.6
Classifier: Programming Language :: Python :: 3.7
